{
  "twii": {
    "price": 41138.85,
    "prev_close": 40769.29,
    "change": 0.91,
    "volume": 0,
    "ma5": 40168.68,
    "ma20": 37826.15,
    "ma60": 34745.12,
    "kd": {
      "k": 90.1,
      "d": 95.2,
      "j": 79.9
    },
    "rsi6": 84.6,
    "macd": {
      "dif": 25391.32,
      "signal": 147655.63,
      "hist": 173046.95
    },
    "atr": 869.1927,
    "vwap": 38498.7354,
    "bb": {
      "upper": 41676.3573,
      "middle": 37826.1486,
      "lower": 33975.94
    },
    "bias": 8.76,
    "macd_signal": "bullish",
    "kdj_j": 79.9,
    "signal": "neutral",
    "ok": true
  },
  "txf": {
    "price": 41138.85,
    "prev_close": 40769.29,
    "change": 0.91,
    "volume": 0,
    "ma5": 40168.68,
    "ma20": 37826.15,
    "ma60": 34745.12,
    "kd": {
      "k": 90.1,
      "d": 95.2,
      "j": 79.9
    },
    "rsi6": 84.6,
    "macd": {
      "dif": 25391.32,
      "signal": 147655.63,
      "hist": 173046.95
    },
    "atr": 869.1927,
    "vwap": 38498.7354,
    "bb": {
      "upper": 41676.3573,
      "middle": 37826.1486,
      "lower": 33975.94
    },
    "bias": 8.76,
    "macd_signal": "bullish",
    "kdj_j": 79.9,
    "signal": "neutral",
    "ok": true
  },
  "2330": {
    "price": 2250.0,
    "prev_close": 2250.0,
    "change": 0.0,
    "volume": 34075250,
    "ma5": 2218.0,
    "ma20": 2105.25,
    "ma60": 1935.7,
    "kd": {
      "k": 70.9,
      "d": 74.8,
      "j": 63.2
    },
    "rsi6": 65.7,
    "macd": {
      "dif": 1099.61,
      "signal": 8081.49,
      "hist": 9181.1
    },
    "atr": 64.016,
    "vwap": 2165.6921,
    "bb": {
      "upper": 2312.4088,
      "middle": 2105.25,
      "lower": 1898.0912
    },
    "bias": 6.88,
    "macd_signal": "bullish",
    "kdj_j": 63.2,
    "signal": "neutral",
    "ok": true
  },
  "spy": {
    "price": 723.77,
    "prev_close": 718.01,
    "change": 0.8,
    "volume": 36643400,
    "ma5": 718.53,
    "ma20": 704.68,
    "ma60": 681.59,
    "kd": {
      "k": 94.4,
      "d": 81.8,
      "j": 119.7
    },
    "rsi6": 76.5,
    "macd": {
      "dif": 92.93,
      "signal": 1192.18,
      "hist": 1285.11
    },
    "atr": 7.6824,
    "vwap": 711.8853,
    "bb": {
      "upper": 732.7565,
      "middle": 704.6805,
      "lower": 676.6045
    },
    "bias": 2.71,
    "macd_signal": "bullish",
    "kdj_j": 119.7,
    "signal": "overbought",
    "ok": true
  },
  "qqq": {
    "price": 681.61,
    "prev_close": 672.88,
    "change": 1.3,
    "volume": 36623100,
    "ma5": 671.59,
    "ma20": 647.07,
    "ma60": 613.63,
    "kd": {
      "k": 96.9,
      "d": 93.1,
      "j": 104.6
    },
    "rsi6": 83.5,
    "macd": {
      "dif": 229.55,
      "signal": 1677.4,
      "hist": 1906.95
    },
    "atr": 9.7061,
    "vwap": 657.6777,
    "bb": {
      "upper": 691.1246,
      "middle": 647.066,
      "lower": 603.0074
    },
    "bias": 5.34,
    "macd_signal": "bullish",
    "kdj_j": 104.6,
    "signal": "overbought",
    "ok": true
  },
  "vix": {
    "price": 17.38,
    "prev_close": 18.29,
    "change": -4.98,
    "volume": 0,
    "ma5": 17.67,
    "ma20": 18.52,
    "ma60": 21.7,
    "kd": {
      "k": 18.4,
      "d": 21.7,
      "j": 11.6
    },
    "rsi6": 40.8,
    "macd": {
      "dif": 0.0,
      "signal": -137.6,
      "hist": -137.6
    },
    "atr": 2.1315,
    "bb": {
      "upper": 20.4558,
      "middle": 18.5175,
      "lower": 16.5792
    },
    "bias": -6.16,
    "macd_signal": "bearish",
    "kdj_j": 11.6,
    "signal": "neutral",
    "ok": true
  },
  "dxy": {
    "price": 98.1,
    "prev_close": 98.48,
    "change": -0.39,
    "volume": 0,
    "ma5": 98.27,
    "ma20": 98.4,
    "ma60": 98.7,
    "kd": {
      "k": 23.2,
      "d": 38.8,
      "j": -8.0
    },
    "rsi6": 37.6,
    "macd": {
      "dif": -1.1,
      "signal": -17.27,
      "hist": -18.37
    },
    "atr": 0.5906,
    "bb": {
      "upper": 98.9421,
      "middle": 98.4028,
      "lower": 97.8635
    },
    "bias": -0.3,
    "macd_signal": "bearish",
    "kdj_j": -8.0,
    "signal": "oversold",
    "ok": true
  },
  "goog": {
    "price": 384.27,
    "prev_close": 379.64,
    "change": 1.22,
    "volume": 15339100,
    "ma5": 375.28,
    "ma20": 342.97,
    "ma60": 315.85,
    "kd": {
      "k": 91.5,
      "d": 94.1,
      "j": 86.2
    },
    "rsi6": 86.4,
    "macd": {
      "dif": 469.78,
      "signal": 1386.95,
      "hist": 1856.73
    },
    "atr": 9.5404,
    "vwap": 355.5779,
    "bb": {
      "upper": 386.9712,
      "middle": 342.9665,
      "lower": 298.9618
    },
    "bias": 12.04,
    "macd_signal": "bullish",
    "kdj_j": 86.2,
    "signal": "neutral",
    "ok": true
  },
  "mu": {
    "price": 640.2,
    "prev_close": 576.45,
    "change": 11.06,
    "volume": 62903700,
    "ma5": 558.9,
    "ma20": 484.83,
    "ma60": 428.75,
    "kd": {
      "k": 93.6,
      "d": 92.6,
      "j": 95.5
    },
    "rsi6": 91.6,
    "macd": {
      "dif": 1389.13,
      "signal": 3097.72,
      "hist": 4486.85
    },
    "atr": 33.0728,
    "vwap": 514.4133,
    "bb": {
      "upper": 597.2276,
      "middle": 484.8315,
      "lower": 372.4354
    },
    "bias": 32.05,
    "macd_signal": "bullish",
    "kdj_j": 95.5,
    "signal": "neutral",
    "ok": true
  },
  "soxx": {
    "price": 482.73,
    "prev_close": 462.06,
    "change": 4.47,
    "volume": 7106900,
    "ma5": 464.39,
    "ma20": 427.12,
    "ma60": 371.2,
    "kd": {
      "k": 93.7,
      "d": 91.7,
      "j": 97.5
    },
    "rsi6": 80.7,
    "macd": {
      "dif": 310.42,
      "signal": 2651.36,
      "hist": 2961.78
    },
    "atr": 13.4975,
    "vwap": 444.378,
    "bb": {
      "upper": 490.706,
      "middle": 427.122,
      "lower": 363.538
    },
    "bias": 13.02,
    "macd_signal": "bullish",
    "kdj_j": 97.5,
    "signal": "neutral",
    "ok": true
  },
  "poet": {
    "price": 9.21,
    "prev_close": 7.11,
    "change": 29.54,
    "volume": 83859700,
    "ma5": 7.47,
    "ma20": 8.33,
    "ma60": 6.88,
    "kd": {
      "k": 31.1,
      "d": 16.5,
      "j": 60.3
    },
    "rsi6": 56.2,
    "macd": {
      "dif": -23.45,
      "signal": 61.84,
      "hist": 38.38
    },
    "atr": 1.5758,
    "vwap": 9.3972,
    "bb": {
      "upper": 12.9735,
      "middle": 8.334,
      "lower": 3.6945
    },
    "bias": 10.56,
    "macd_signal": "bullish",
    "kdj_j": 60.3,
    "signal": "neutral",
    "ok": true
  },
  "arm": {
    "price": 208.84,
    "prev_close": 203.26,
    "change": 2.75,
    "volume": 7531000,
    "ma5": 207.06,
    "ma20": 184.56,
    "ma60": 148.47,
    "kd": {
      "k": 36.6,
      "d": 45.8,
      "j": 18.3
    },
    "rsi6": 59.7,
    "macd": {
      "dif": 52.77,
      "signal": 1712.29,
      "hist": 1765.06
    },
    "atr": 12.9843,
    "vwap": 201.5069,
    "bb": {
      "upper": 236.5179,
      "middle": 184.5618,
      "lower": 132.6056
    },
    "bias": 13.16,
    "macd_signal": "bullish",
    "kdj_j": 18.3,
    "signal": "neutral",
    "ok": true
  },
  "aapl": {
    "price": 284.18,
    "prev_close": 276.83,
    "change": 2.66,
    "volume": 49101300,
    "ma5": 276.53,
    "ma20": 268.79,
    "ma60": 262.53,
    "kd": {
      "k": 86.3,
      "d": 69.1,
      "j": 120.6
    },
    "rsi6": 74.3,
    "macd": {
      "dif": 125.85,
      "signal": 399.04,
      "hist": 524.89
    },
    "atr": 6.6507,
    "vwap": 272.745,
    "bb": {
      "upper": 282.7797,
      "middle": 268.7915,
      "lower": 254.8033
    },
    "bias": 5.73,
    "macd_signal": "bullish",
    "kdj_j": 120.6,
    "signal": "overbought",
    "ok": true
  },
  "tsla": {
    "price": 389.37,
    "prev_close": 392.51,
    "change": -0.8,
    "volume": 47443000,
    "ma5": 385.43,
    "ma20": 376.71,
    "ma60": 388.44,
    "kd": {
      "k": 66.5,
      "d": 76.7,
      "j": 46.2
    },
    "rsi6": 61.2,
    "macd": {
      "dif": 220.43,
      "signal": 0.48,
      "hist": 220.91
    },
    "atr": 14.186,
    "vwap": 385.3446,
    "bb": {
      "upper": 410.4077,
      "middle": 376.709,
      "lower": 343.0103
    },
    "bias": 3.36,
    "macd_signal": "bullish",
    "kdj_j": 46.2,
    "signal": "neutral",
    "ok": true
  },
  "nbis": {
    "price": 175.92,
    "prev_close": 176.42,
    "change": -0.28,
    "volume": 11682100,
    "ma5": 157.25,
    "ma20": 152.74,
    "ma60": 120.04,
    "kd": {
      "k": 91.5,
      "d": 82.6,
      "j": 109.1
    },
    "rsi6": 75.9,
    "macd": {
      "dif": 69.7,
      "signal": 986.91,
      "hist": 1056.61
    },
    "atr": 12.2561,
    "vwap": 155.2575,
    "bb": {
      "upper": 179.1317,
      "middle": 152.743,
      "lower": 126.3543
    },
    "bias": 15.18,
    "macd_signal": "bullish",
    "kdj_j": 109.1,
    "signal": "overbought",
    "ok": true
  },
  "smr": {
    "price": 11.87,
    "prev_close": 12.18,
    "change": -2.55,
    "volume": 18436000,
    "ma5": 11.99,
    "ma20": 11.56,
    "ma60": 12.17,
    "kd": {
      "k": 30.9,
      "d": 36.6,
      "j": 19.4
    },
    "rsi6": 47.9,
    "macd": {
      "dif": 6.76,
      "signal": 10.0,
      "hist": 16.76
    },
    "atr": 1.086,
    "vwap": 12.3357,
    "bb": {
      "upper": 14.0218,
      "middle": 11.556,
      "lower": 9.0902
    },
    "bias": 2.68,
    "macd_signal": "bullish",
    "kdj_j": 19.4,
    "signal": "neutral",
    "ok": true
  },
  "avgo": {
    "price": 427.36,
    "prev_close": 416.5,
    "change": 2.61,
    "volume": 21082500,
    "ma5": 417.6,
    "ma20": 400.63,
    "ma60": 349.69,
    "kd": {
      "k": 84.4,
      "d": 74.8,
      "j": 103.7
    },
    "rsi6": 69.4,
    "macd": {
      "dif": -20.17,
      "signal": 2143.88,
      "hist": 2123.71
    },
    "atr": 13.1835,
    "vwap": 411.2494,
    "bb": {
      "upper": 444.6259,
      "middle": 400.6275,
      "lower": 356.6291
    },
    "bias": 6.67,
    "macd_signal": "bullish",
    "kdj_j": 103.7,
    "signal": "overbought",
    "ok": true
  },
  "cohr": {
    "price": 335.73,
    "prev_close": 329.89,
    "change": 1.77,
    "volume": 5519000,
    "ma5": 323.95,
    "ma20": 321.84,
    "ma60": 273.34,
    "kd": {
      "k": 67.9,
      "d": 57.6,
      "j": 88.5
    },
    "rsi6": 64.2,
    "macd": {
      "dif": -212.72,
      "signal": 1720.94,
      "hist": 1508.22
    },
    "atr": 22.279,
    "vwap": 328.8247,
    "bb": {
      "upper": 360.8161,
      "middle": 321.8415,
      "lower": 282.8669
    },
    "bias": 4.32,
    "macd_signal": "bullish",
    "kdj_j": 88.5,
    "signal": "neutral",
    "ok": true
  },
  "amkr": {
    "price": 76.71,
    "prev_close": 70.96,
    "change": 8.1,
    "volume": 6103100,
    "ma5": 71.82,
    "ma20": 67.31,
    "ma60": 53.66,
    "kd": {
      "k": 82.3,
      "d": 55.7,
      "j": 135.6
    },
    "rsi6": 74.0,
    "macd": {
      "dif": -10.31,
      "signal": 601.17,
      "hist": 590.86
    },
    "atr": 4.2914,
    "vwap": 70.8782,
    "bb": {
      "upper": 81.6024,
      "middle": 67.314,
      "lower": 53.0256
    },
    "bias": 13.97,
    "macd_signal": "bullish",
    "kdj_j": 135.6,
    "signal": "overbought",
    "ok": true
  },
  "glxy": {
    "price": 28.26,
    "prev_close": 28.26,
    "change": 0.0,
    "volume": 0,
    "ma5": 30.0,
    "ma20": 29.68,
    "ma60": 33.4,
    "kd": {
      "k": 9.2,
      "d": 22.2,
      "j": -16.9
    },
    "rsi6": 39.6,
    "macd": {
      "dif": 13.1,
      "signal": -82.23,
      "hist": -69.13
    },
    "atr": 2.2623,
    "vwap": 29.5671,
    "bb": {
      "upper": 32.7146,
      "middle": 29.6785,
      "lower": 26.6424
    },
    "bias": -4.78,
    "macd_signal": "bearish",
    "kdj_j": -16.9,
    "signal": "oversold",
    "ok": true
  },
  "wolf": {
    "price": 36.63,
    "prev_close": 35.94,
    "change": 1.92,
    "volume": 10547700,
    "ma5": 32.9,
    "ma20": 27.45,
    "ma60": 21.06,
    "kd": {
      "k": 76.1,
      "d": 85.4,
      "j": 57.6
    },
    "rsi6": 75.1,
    "macd": {
      "dif": 90.37,
      "signal": 293.77,
      "hist": 384.14
    },
    "atr": 3.5134,
    "vwap": 30.2381,
    "bb": {
      "upper": 36.4303,
      "middle": 27.4465,
      "lower": 18.4627
    },
    "bias": 33.44,
    "macd_signal": "bullish",
    "kdj_j": 57.6,
    "signal": "neutral",
    "ok": true
  },
  "oust": {
    "price": 28.6,
    "prev_close": 28.15,
    "change": 1.6,
    "volume": 5883300,
    "ma5": 27.14,
    "ma20": 25.25,
    "ma60": 21.74,
    "kd": {
      "k": 66.3,
      "d": 52.1,
      "j": 94.8
    },
    "rsi6": 69.3,
    "macd": {
      "dif": 13.91,
      "signal": 161.95,
      "hist": 175.86
    },
    "atr": 2.0434,
    "vwap": 27.4124,
    "bb": {
      "upper": 30.613,
      "middle": 25.252,
      "lower": 19.891
    },
    "bias": 13.27,
    "macd_signal": "bullish",
    "kdj_j": 94.8,
    "signal": "neutral",
    "ok": true
  },
  "irdm": {
    "price": 39.23,
    "prev_close": 39.89,
    "change": -1.65,
    "volume": 1415700,
    "ma5": 38.8,
    "ma20": 38.59,
    "ma60": 29.63,
    "kd": {
      "k": 50.4,
      "d": 47.7,
      "j": 55.9
    },
    "rsi6": 53.9,
    "macd": {
      "dif": -51.91,
      "signal": 281.73,
      "hist": 229.82
    },
    "atr": 2.3159,
    "vwap": 40.3015,
    "bb": {
      "upper": 44.0788,
      "middle": 38.591,
      "lower": 33.1032
    },
    "bias": 1.66,
    "macd_signal": "bullish",
    "kdj_j": 55.9,
    "signal": "neutral",
    "ok": true
  },
  "coin": {
    "price": 197.75,
    "prev_close": 202.99,
    "change": -2.58,
    "volume": 10003000,
    "ma5": 192.3,
    "ma20": 191.84,
    "ma60": 184.37,
    "kd": {
      "k": 64.4,
      "d": 59.3,
      "j": 74.6
    },
    "rsi6": 54.7,
    "macd": {
      "dif": 13.51,
      "signal": 268.25,
      "hist": 281.77
    },
    "atr": 11.8649,
    "vwap": 198.869,
    "bb": {
      "upper": 216.5144,
      "middle": 191.8375,
      "lower": 167.1606
    },
    "bias": 3.08,
    "macd_signal": "bullish",
    "kdj_j": 74.6,
    "signal": "neutral",
    "ok": true
  },
  "last_updated": "2026-05-06T14:31:37.206096+08:00"
}